README.md
setup.py
tradingts/__init__.py
tradingts/get_response.py
tradingts/ts_main.py
tradingts/ts_python.py
tradingts.egg-info/PKG-INFO
tradingts.egg-info/SOURCES.txt
tradingts.egg-info/dependency_links.txt
tradingts.egg-info/top_level.txt