Metadata-Version: 2.1
Name: tradingts
Version: 0.0.4
Summary: ts python package
Home-page: https://github.com/
Author: ts_python_user
License: UNKNOWN
Platform: UNKNOWN
Classifier: Programming Language :: Python :: 3
Classifier: License :: OSI Approved :: MIT License
Classifier: Operating System :: OS Independent
